MomentBook/__init__.py
MomentBook/cli.py
MomentBook/database_funcs.py
MomentBook/queries.py
Moment_Book-0.0.6.dist-info/METADATA
Moment_Book-0.0.6.dist-info/WHEEL
Moment_Book-0.0.6.dist-info/top_level.txt
Moment_Book-0.0.6.dist-info/RECORD
